instaview/__init__.py
instaview/cli.py
instaview/scraper.py
instaview-0.1.7.dist-info/entry_points.txt
instaview-0.1.7.dist-info/WHEEL
instaview-0.1.7.dist-info/METADATA
instaview-0.1.7.dist-info/RECORD
